functional_functions/__init__.py
functional_functions/creds.env.sample
functional_functions/ff_classes.py
functional_functions/settings.py.sample
functional_functions-0.6.1.dist-info/LICENSE
functional_functions-0.6.1.dist-info/METADATA
functional_functions-0.6.1.dist-info/WHEEL
functional_functions-0.6.1.dist-info/top_level.txt
functional_functions-0.6.1.dist-info/RECORD
