Metadata-Version: 2.1
Name: functional-functions
Version: 0.6.1
Summary: Commonly used functions by the Compass FBI Team
Home-page: https://github.com/UrbanCompass/Functional-Functions
Author: Lawrence Chin
Author-email: lawrence.chin@compass.com
Classifier: Programming Language :: Python :: 3
Classifier: License :: OSI Approved :: MIT License
Classifier: Operating System :: OS Independent
Requires-Python: >=3.6
License-File: LICENSE
Requires-Dist: snowflake-connector-python (>=2.1.1)
Requires-Dist: snowflake-sqlalchemy (>=1.2.4)
Requires-Dist: pandas (>=1.1.4)
Requires-Dist: numpy (>=1.19.4)
Requires-Dist: pytz (>=2020.4)
Requires-Dist: pyarrow (<=6.0.0,>=5.0.0)
Requires-Dist: boto3 (>=1.18.54)
Requires-Dist: redshift-connector (>=2.0.902)
Requires-Dist: databricks-sql-connector (>=2.0.0b1)
Requires-Dist: python-dotenv (>=0.19.0)
